.gitignore
.gitlab-ci.yml
CHANGELOG.md
LICENSE.md
README.md
setup.py
sigmentation/__init__.py
sigmentation/algorithm.py
sigmentation/cli.py
sigmentation/optimization.py
sigmentation/processing.py
sigmentation.egg-info/PKG-INFO
sigmentation.egg-info/SOURCES.txt
sigmentation.egg-info/dependency_links.txt
sigmentation.egg-info/entry_points.txt
sigmentation.egg-info/requires.txt
sigmentation.egg-info/top_level.txt